[
  {
    "id": "lau-mam-can-tho",
    "title": "Lẩu mắm Cần Thơ",
    "image": "LauMamCT.png",
    "shortDescription": "Món lẩu đậm đà hương vị miền Tây, với nhiều loại cá và rau dân dã."
  },
  {
    "id": "banh-tet-la-cam",
    "title": "Bánh tét lá cẩm Cần Thơ",
    "image": "BanhTetLaLotCT.png",
    "shortDescription": "Món bánh truyền thống với màu tím đẹp mắt, nhân đậu mỡ trứng mặn."
  },
  {
    "id": "chao-long-cai-tac",
    "title": "Cháo lòng Cái Tắc",
    "image": "ChaoLongCaiTac.png",
    "shortDescription": "Món cháo lòng nổi tiếng, ăn kèm lòng heo và gia vị đặc trưng."
  },
  {
    "id": "bun-nuoc-leo",
    "title": "Bún nước lèo",
    "image": "BunNuocLeo.png",
    "shortDescription": "Đậm đà nước dùng mắm và cá, ăn kèm rau sống tươi ngon."
  },
  {
    "id": "bun-goi-da",
    "title": "Bún gỏi dà",
    "image": "BunGoiDa.png",
    "shortDescription": "Hương vị chua ngọt cay hài hoà, đặc sản miền sông nước."
  }
]
